reflex_highchart/__init__.py
reflex_highchart/reflex_highchart.py
reflex_highchart-0.0.1.dist-info/METADATA
reflex_highchart-0.0.1.dist-info/WHEEL
reflex_highchart-0.0.1.dist-info/top_level.txt
reflex_highchart-0.0.1.dist-info/RECORD
