Metadata-Version: 2.1
Name: reflex-highchart
Version: 0.0.1
Summary: reflex-highcharts is a powerful component designed to integrate the popular charting library,
Author-email: Jitendra Mishra <jitendra29mishra@gmail.com>
License: Apache-2.0
Project-URL: Homepage, https://github.com/jmishra01/reflex-highchart
Keywords: reflex,reflex-custom-components,Highchart,Visualization,Python,SSR
Classifier: Development Status :: 4 - Beta
Requires-Python: >=3.8
Requires-Dist: reflex>=0.4.2
Provides-Extra: dev
Requires-Dist: build; extra == "dev"
Requires-Dist: twine; extra == "dev"
